setup.py
odoo/addons/cooperator_sponsorship/CHANGELOG.md
odoo/addons/cooperator_sponsorship/README.rst
odoo/addons/cooperator_sponsorship/__init__.py
odoo/addons/cooperator_sponsorship/__manifest__.py
odoo/addons/cooperator_sponsorship/i18n/ca_ES.po
odoo/addons/cooperator_sponsorship/i18n/es.po
odoo/addons/cooperator_sponsorship/models/__init__.py
odoo/addons/cooperator_sponsorship/models/cooperative_membership.py
odoo/addons/cooperator_sponsorship/models/res_company.py
odoo/addons/cooperator_sponsorship/models/res_partner.py
odoo/addons/cooperator_sponsorship/models/subscription_request.py
odoo/addons/cooperator_sponsorship/tests/__init__.py
odoo/addons/cooperator_sponsorship/tests/helper.py
odoo/addons/cooperator_sponsorship/tests/models/__init__.py
odoo/addons/cooperator_sponsorship/tests/models/test_res_partner.py
odoo/addons/cooperator_sponsorship/tests/models/test_subscription.py
odoo/addons/cooperator_sponsorship/tests/wizards/__init__.py
odoo/addons/cooperator_sponsorship/tests/wizards/test_member_wizard.py
odoo/addons/cooperator_sponsorship/views/menus.xml
odoo/addons/cooperator_sponsorship/views/res_company_view.xml
odoo/addons/cooperator_sponsorship/views/res_partner_view.xml
odoo/addons/cooperator_sponsorship/views/subscription_request_view.xml
odoo/addons/cooperator_sponsorship/wizards/__init__.py
odoo/addons/cooperator_sponsorship/wizards/sponsee_member_wizard.py
odoo/addons/cooperator_sponsorship/wizards/sponsee_member_wizard.xml
odoo_addon_cooperator_sponsorship.egg-info/PKG-INFO
odoo_addon_cooperator_sponsorship.egg-info/SOURCES.txt
odoo_addon_cooperator_sponsorship.egg-info/dependency_links.txt
odoo_addon_cooperator_sponsorship.egg-info/not-zip-safe
odoo_addon_cooperator_sponsorship.egg-info/requires.txt
odoo_addon_cooperator_sponsorship.egg-info/top_level.txt