Metadata-Version: 1.2
Name: odoo-addon-cooperator-sponsorship
Version: 16.0.1.0.0
Summary: Odoo Sponsorship module for cooperator addon.
Home-page: https://coopdevs.org
Author: Coopdevs Treball SCCL
License: AGPL-3
Platform: UNKNOWN
Classifier: Programming Language :: Python
Classifier: Framework :: Odoo
Classifier: Framework :: Odoo :: 16.0
Classifier: License :: OSI Approved :: GNU Affero General Public License v3
Requires-Python: >=3.10
